CHANGES.rst
MANIFEST.in
README.rst
setup.py
bin/rakutenma
rakutenma/__init__.py
rakutenma/rakutenma.py
rakutenma/scw.py
rakutenma/trie.py
rakutenma.egg-info/PKG-INFO
rakutenma.egg-info/SOURCES.txt
rakutenma.egg-info/dependency_links.txt
rakutenma.egg-info/top_level.txt
rakutenma/model/model_ja.json
rakutenma/model/model_ja.min.json