Metadata-Version: 1.1
Name: rakutenma
Version: 0.3.3
Summary: morphological analyzer (word segmentor + PoS Tagger) for Chinese and Japanese
Home-page: https://github.com/ikegami-yukino/rakutenma-python
Author: Yukino Ikegami
Author-email: yknikgm@gmail.com
License: Apache Software License
Keywords: morphological analyzer,word segmentor,PoS Tagger
Platform: POSIX
Platform: Windows
Platform: Unix
Platform: MacOS
Classifier: Development Status :: 3 - Alpha
Classifier: Intended Audience :: Developers
Classifier: Intended Audience :: Information Technology
Classifier: License :: OSI Approved :: Apache Software License
Classifier: Natural Language :: Japanese
Classifier: Natural Language :: Chinese (Simplified)
Classifier: Natural Language :: Chinese (Traditional)
Classifier: Programming Language :: Python :: 2.6
Classifier: Programming Language :: Python :: 2.7
Classifier: Programming Language :: Python :: 3.3
Classifier: Programming Language :: Python :: 3.4
Classifier: Programming Language :: Python :: 3.5
Classifier: Programming Language :: Python :: 3.6
Classifier: Topic :: Text Processing :: Linguistic
